[{"code": "SZ399393", "name": "\u56fd\u8bc1\u5730\u4ea7", "ttype": "3", "pe": 0, "pb": 0.7056, "pePercentile": 0, "pbPercentile": 0.0688, "roe": 0, "yeild": 0.0186, "ts": 1783958400000, "evaType": "low", "evaTypeInt": 0, "bondYeild": 0.05, "beginAt": 1459353600000, "createdAt": 1784025123863, "updatedAt": 1784025123863, "pbFlag": true, "pbOverHistory": 0.9312, "peOverHistory": 1, "date": "07-14"}, {"code": "SZ399812", "name": "\u517b\u8001\u4ea7\u4e1a", "ttype": "3", "pe": 11.2259, "pb": 1.7499, "pePercentile": 0.014, "pbPercentile": 0.032, "roe": 0.1559, "yeild": 0.0257, "ts": 1783958400000, "evaType": "low", "evaTypeInt": 0, "bondYeild": 0.05, "beginAt": 1459353600000, "createdAt": 1784043121121, "updatedAt": 1784043121121, "pbFlag": false, "pbOverHistory": 0.968, "peOverHistory": 0.986, "date": "07-14"}, {"code": "SZ399975", "name": "\u8bc1\u5238\u516c\u53f8", "ttype": "3", "pe": 15.1927, "pb": 1.3113, "pePercentile": 0.062, "pbPercentile": 0.2224, "roe": 0.0863, "yeild": 0.0202, "ts": 1783958400000, "evaType": "low", "evaTypeInt": 0, "bondYeild": 0.05, "beginAt": 1459353600000, "createdAt": 1784025121567, "updatedAt": 1784025121567, "pbFlag": true, "pbOverHistory": 0.7776, "peOverHistory": 0.938, "date": "07-14"}, {"code": "CSIH11136", "name": "\u4e2d\u56fd\u4e92\u8054", "ttype": "3", "pe": 16.2142, "pb": 2.0951, "pePercentile": 0.034, "pbPercentile": 0.0124, "roe": 0.1292, "yeild": 0.0113, "ts": 1783958400000, "evaType": "low", "evaTypeInt": 0, "bondYeild": 0.05, "beginAt": 1459353600000, "createdAt": 1784079121166, "updatedAt": 1784079121166, "pbFlag": false, "pbOverHistory": 0.9876, "peOverHistory": 0.966, "date": "07-14"}, {"code": "CSIH30533", "name": "\u4e2d\u6982\u4e92\u805450", "ttype": "3", "pe": 16.2274, "pb": 2.1007, "pePercentile": 0.0192, "pbPercentile": 0.014, "roe": 0.1295, "yeild": 0.0106, "ts": 1783958400000, "evaType": "low", "evaTypeInt": 0, "bondYeild": 0.05, "beginAt": 1459353600000, "createdAt": 1784079121573, "updatedAt": 1784079121573, "pbFlag": false, "pbOverHistory": 0.986, "peOverHistory": 0.9808, "date": "07-14"}, {"code": "CSIH30094", "name": "\u6d88\u8d39\u7ea2\u5229", "ttype": "2", "pe": 17.5884, "pb": 3.3324, "pePercentile": 0.0104, "pbPercentile": 0.008, "roe": 0.1895, "yeild": 0.0444, "ts": 1783958400000, "evaType": "low", "evaTypeInt": 0, "bondYeild": 0.05, "beginAt": 1459267200000, "createdAt": 1784043123370, "updatedAt": 1784043123370, "pbFlag": false, "pbOverHistory": 0.992, "peOverHistory": 0.9896, "date": "07-14"}, {"code": "SZ399997", "name": "\u4e2d\u8bc1\u767d\u9152", "ttype": "3", "pe": 18.2198, "pb": 3.8029, "pePercentile": 0.0412, "pbPercentile": 0.0176, "roe": 0.2087, "yeild": 0.0452, "ts": 1783958400000, "evaType": "low", "evaTypeInt": 0, "bondYeild": 0.05, "beginAt": 1459353600000, "createdAt": 1784043120861, "updatedAt": 1784043120861, "pbFlag": false, "pbOverHistory": 0.9824, "peOverHistory": 0.9588, "date": "07-14"}, {"code": "SH000932", "name": "\u4e3b\u8981\u6d88\u8d39", "ttype": "3", "pe": 19.3224, "pb": 3.2695, "pePercentile": 0.0484, "pbPercentile": 0.0096, "roe": 0.1692, "yeild": 0.0404, "ts": 1783958400000, "evaType": "low", "evaTypeInt": 0, "bondYeild": 0.05, "beginAt": 1459353600000, "createdAt": 1784043121920, "updatedAt": 1784043121920, "pbFlag": false, "pbOverHistory": 0.9904, "peOverHistory": 0.9516, "date": "07-14"}, {"code": "SZ399396", "name": "\u56fd\u8bc1\u98df\u54c1", "ttype": "3", "pe": 19.4987, "pb": 3.4098, "pePercentile": 0.0188, "pbPercentile": 0.0092, "roe": 0.1749, "yeild": 0.0406, "ts": 1783958400000, "evaType": "low", "evaTypeInt": 0, "bondYeild": 0.05, "beginAt": 1459353600000, "createdAt": 1784043121028, "updatedAt": 1784043121028, "pbFlag": false, "pbOverHistory": 0.9908, "peOverHistory": 0.9812, "date": "07-14"}, {"code": "SH000989", "name": "\u5168\u6307\u53ef\u9009", "ttype": "3", "pe": 20.6805, "pb": 2.0964, "pePercentile": 0.192, "pbPercentile": 0.18, "roe": 0.1014, "yeild": 0.0274, "ts": 1783958400000, "evaType": "low", "evaTypeInt": 0, "bondYeild": 0.05, "beginAt": 1459353600000, "createdAt": 1784043121197, "updatedAt": 1784043121197, "pbFlag": false, "pbOverHistory": 0.82, "peOverHistory": 0.808, "date": "07-14"}, {"code": "SZ399989", "name": "\u4e2d\u8bc1\u533b\u7597", "ttype": "3", "pe": 28.9128, "pb": 3.2581, "pePercentile": 0.1388, "pbPercentile": 0.0576, "roe": 0.1127, "yeild": 0.0143, "ts": 1783958400000, "evaType": "low", "evaTypeInt": 0, "bondYeild": 0.05, "beginAt": 1459353600000, "createdAt": 1784043122992, "updatedAt": 1784043122992, "pbFlag": false, "pbOverHistory": 0.9424, "peOverHistory": 0.8612, "date": "07-14"}, {"code": "SH000919", "name": "300\u4ef7\u503c", "ttype": "2", "pe": 8.7265, "pb": 0.873, "pePercentile": 0.6324, "pbPercentile": 0.276, "roe": 0.1, "yeild": 0.0455, "ts": 1783958400000, "evaType": "mid", "evaTypeInt": 1, "bondYeild": 0.05, "beginAt": 1459353600000, "createdAt": 1784043122011, "updatedAt": 1784043122011, "pbFlag": false, "pbOverHistory": 0.724, "peOverHistory": 0.3676, "date": "07-14"}, {"code": "HSFML25", "name": "\u9999\u6e2f\u5927\u76d8", "ttype": "1", "pe": 9.2649, "pb": 0.9315, "pePercentile": 0.528, "pbPercentile": 0.2708, "roe": 0.1005, "yeild": 0.0314, "ts": 1783958400000, "evaType": "mid", "evaTypeInt": 1, "bondYeild": 0.05, "beginAt": 1459353600000, "createdAt": 1784079120702, "updatedAt": 1784079120702, "pbFlag": false, "pbOverHistory": 0.7292, "peOverHistory": 0.472, "date": "07-14"}, {"code": "SZ399971", "name": "\u4e2d\u8bc1\u4f20\u5a92", "ttype": "3", "pe": 32.1883, "pb": 2.1415, "pePercentile": 0.3452, "pbPercentile": 0.2004, "roe": 0.0665, "yeild": 0.0224, "ts": 1783958400000, "evaType": "mid", "evaTypeInt": 1, "bondYeild": 0.05, "beginAt": 1459353600000, "createdAt": 1784025123769, "updatedAt": 1784025123769, "pbFlag": false, "pbOverHistory": 0.7996, "peOverHistory": 0.6548, "date": "07-14"}, {"code": "SH000991", "name": "\u5168\u6307\u533b\u836f", "ttype": "3", "pe": 32.7658, "pb": 3.0731, "pePercentile": 0.3988, "pbPercentile": 0.1108, "roe": 0.0938, "yeild": 0.0173, "ts": 1783958400000, "evaType": "mid", "evaTypeInt": 1, "bondYeild": 0.05, "beginAt": 1459353600000, "createdAt": 1784043121274, "updatedAt": 1784043121274, "pbFlag": false, "pbOverHistory": 0.8892, "peOverHistory": 0.6012, "date": "07-14"}, {"code": "SH000978", "name": "\u533b\u836f100", "ttype": "3", "pe": 33.2603, "pb": 3.1551, "pePercentile": 0.444, "pbPercentile": 0.1324, "roe": 0.0949, "yeild": 0.0169, "ts": 1783958400000, "evaType": "mid", "evaTypeInt": 1, "bondYeild": 0.05, "beginAt": 1459353600000, "createdAt": 1784043122282, "updatedAt": 1784043122282, "pbFlag": false, "pbOverHistory": 0.8676, "peOverHistory": 0.556, "date": "07-14"}, {"code": "SZ399986", "name": "\u4e2d\u8bc1\u94f6\u884c", "ttype": "3", "pe": 6.7824, "pb": 0.6509, "pePercentile": 0.7776, "pbPercentile": 0.3312, "roe": 0.096, "yeild": 0.0528, "ts": 1783958400000, "evaType": "high", "evaTypeInt": 2, "bondYeild": 0.05, "beginAt": 1459353600000, "createdAt": 1784025121109, "updatedAt": 1784025121109, "pbFlag": true, "pbOverHistory": 0.6688, "peOverHistory": 0.2224, "date": "07-14"}, {"code": "SPACEVCP", "name": "\u6807\u666e\u4ef7\u503c", "ttype": "2", "pe": 6.8257, "pb": 0.7517, "pePercentile": 0.6028, "pbPercentile": 0.5964, "roe": 0.1101, "yeild": 0.0453, "ts": 1783958400000, "evaType": "high", "evaTypeInt": 2, "bondYeild": 0.05, "beginAt": 1459440000000, "createdAt": 1784025120209, "updatedAt": 1784025120209, "pbFlag": false, "pbOverHistory": 0.4036, "peOverHistory": 0.3972, "date": "07-14"}, {"code": "CSI931157", "name": "\u7ea2\u5229\u6210\u957fLV", "ttype": "2", "pe": 7.6173, "pb": 0.8187, "pePercentile": 0.5186, "pbPercentile": 0.3826, "roe": 0.1075, "yeild": 0.0474, "ts": 1783958400000, "evaType": "high", "evaTypeInt": 2, "bondYeild": 0.05, "beginAt": 1556121600000, "createdAt": 1784043122595, "updatedAt": 1784043122595, "pbFlag": false, "pbOverHistory": 0.6174, "peOverHistory": 0.4814, "date": "07-14"}, {"code": "CSIH30269", "name": "\u7ea2\u5229\u4f4e\u6ce2", "ttype": "2", "pe": 8.0026, "pb": 0.8175, "pePercentile": 0.7116, "pbPercentile": 0.52, "roe": 0.1022, "yeild": 0.0529, "ts": 1783958400000, "evaType": "high", "evaTypeInt": 2, "bondYeild": 0.05, "beginAt": 1459353600000, "createdAt": 1784043121754, "updatedAt": 1784043121754, "pbFlag": false, "pbOverHistory": 0.48, "peOverHistory": 0.2884, "date": "07-14"}, {"code": "SH000922", "name": "\u4e2d\u8bc1\u7ea2\u5229", "ttype": "2", "pe": 8.1803, "pb": 0.7975, "pePercentile": 0.674, "pbPercentile": 0.3988, "roe": 0.0975, "yeild": 0.0509, "ts": 1783958400000, "evaType": "high", "evaTypeInt": 2, "bondYeild": 0.05, "beginAt": 1459353600000, "createdAt": 1784043120770, "updatedAt": 1784043120770, "pbFlag": false, "pbOverHistory": 0.6012, "peOverHistory": 0.326, "date": "07-14"}, {"code": "SH000015", "name": "\u4e0a\u8bc1\u7ea2\u5229", "ttype": "2", "pe": 8.3846, "pb": 0.8045, "pePercentile": 0.8752, "pbPercentile": 0.5616, "roe": 0.0959, "yeild": 0.0507, "ts": 1783958400000, "evaType": "high", "evaTypeInt": 2, "bondYeild": 0.05, "beginAt": 1459180800000, "createdAt": 1784025124244, "updatedAt": 1784025124244, "pbFlag": false, "pbOverHistory": 0.4384, "peOverHistory": 0.1248, "date": "07-14"}, {"code": "CSI930740", "name": "300\u7ea2\u5229LV", "ttype": "2", "pe": 8.5945, "pb": 0.8356, "pePercentile": 0.666, "pbPercentile": 0.3208, "roe": 0.0972, "yeild": 0.0493, "ts": 1783958400000, "evaType": "high", "evaTypeInt": 2, "bondYeild": 0.05, "beginAt": 1458576000000, "createdAt": 1784043122833, "updatedAt": 1784043122833, "pbFlag": false, "pbOverHistory": 0.6792, "peOverHistory": 0.334, "date": "07-14"}, {"code": "CSPSADRP", "name": "\u6807\u666e\u7ea2\u5229", "ttype": "2", "pe": 8.9648, "pb": 0.9373, "pePercentile": 0.9168, "pbPercentile": 0.5976, "roe": 0.1046, "yeild": 0.0502, "ts": 1783958400000, "evaType": "high", "evaTypeInt": 2, "bondYeild": 0.05, "beginAt": 1459267200000, "createdAt": 1784043122713, "updatedAt": 1784043122713, "pbFlag": false, "pbOverHistory": 0.4024, "peOverHistory": 0.0832, "date": "07-14"}, {"code": "SH000925", "name": "\u57fa\u672c\u976250", "ttype": "2", "pe": 9.446, "pb": 0.9784, "pePercentile": 0.6048, "pbPercentile": 0.362, "roe": 0.1036, "yeild": 0.0428, "ts": 1783958400000, "evaType": "high", "evaTypeInt": 2, "bondYeild": 0.05, "beginAt": 1459353600000, "createdAt": 1784043121459, "updatedAt": 1784043121459, "pbFlag": false, "pbOverHistory": 0.638, "peOverHistory": 0.3952, "date": "07-14"}, {"code": "HKHSCEI", "name": "\u56fd\u4f01\u6307\u6570", "ttype": "1", "pe": 9.7005, "pb": 0.9381, "pePercentile": 0.7176, "pbPercentile": 0.4324, "roe": 0.0967, "yeild": 0.0301, "ts": 1783958400000, "evaType": "high", "evaTypeInt": 2, "bondYeild": 0.05, "beginAt": 1459353600000, "createdAt": 1784079120599, "updatedAt": 1784079120599, "pbFlag": false, "pbOverHistory": 0.5676, "peOverHistory": 0.2824, "date": "07-14"}, {"code": "SZ399550", "name": "\u592e\u89c650", "ttype": "2", "pe": 9.8535, "pb": 0.99, "pePercentile": 0.7088, "pbPercentile": 0.1436, "roe": 0.1005, "yeild": 0.0434, "ts": 1783958400000, "evaType": "high", "evaTypeInt": 2, "bondYeild": 0.05, "beginAt": 1459267200000, "createdAt": 1784043121552, "updatedAt": 1784043121552, "pbFlag": false, "pbOverHistory": 0.8564, "peOverHistory": 0.2912, "date": "07-14"}, {"code": "SH000170", "name": "50AH\u4f18\u9009", "ttype": "1", "pe": 9.9216, "pb": 1.1694, "pePercentile": 0.592, "pbPercentile": 0.676, "roe": 0.1179, "yeild": 0.028, "ts": 1783958400000, "evaType": "high", "evaTypeInt": 2, "bondYeild": 0.05, "beginAt": 1459353600000, "createdAt": 1784043120523, "updatedAt": 1784043120523, "pbFlag": false, "pbOverHistory": 0.324, "peOverHistory": 0.408, "date": "07-14"}, {"code": "SH000016", "name": "\u4e0a\u8bc150", "ttype": "1", "pe": 11.5044, "pb": 1.2454, "pePercentile": 0.7912, "pbPercentile": 0.5688, "roe": 0.1083, "yeild": 0.035, "ts": 1783958400000, "evaType": "high", "evaTypeInt": 2, "bondYeild": 0.05, "beginAt": 1459353600000, "createdAt": 1784043120233, "updatedAt": 1784043120233, "pbFlag": false, "pbOverHistory": 0.4312, "peOverHistory": 0.2088, "date": "07-14"}, {"code": "HKHSI", "name": "\u6052\u751f\u6307\u6570", "ttype": "1", "pe": 11.6653, "pb": 1.1611, "pePercentile": 0.706, "pbPercentile": 0.676, "roe": 0.0995, "yeild": 0.0325, "ts": 1783958400000, "evaType": "high", "evaTypeInt": 2, "bondYeild": 0.05, "beginAt": 1459353600000, "createdAt": 1784079120514, "updatedAt": 1784079120514, "pbFlag": false, "pbOverHistory": 0.324, "peOverHistory": 0.294, "date": "07-14"}, {"code": "SH000010", "name": "\u4e0a\u8bc1180", "ttype": "1", "pe": 12.0626, "pb": 1.2248, "pePercentile": 0.7864, "pbPercentile": 0.4176, "roe": 0.1015, "yeild": 0.0312, "ts": 1783958400000, "evaType": "high", "evaTypeInt": 2, "bondYeild": 0.05, "beginAt": 1459353600000, "createdAt": 1784043122099, "updatedAt": 1784043122099, "pbFlag": false, "pbOverHistory": 0.5824, "peOverHistory": 0.2136, "date": "07-14"}, {"code": "SH000300", "name": "\u6caa\u6df1300", "ttype": "1", "pe": 14.4576, "pb": 1.468, "pePercentile": 0.8864, "pbPercentile": 0.5396, "roe": 0.1015, "yeild": 0.0267, "ts": 1783958400000, "evaType": "high", "evaTypeInt": 2, "bondYeild": 0.05, "beginAt": 1459353600000, "createdAt": 1784043120335, "updatedAt": 1784043120335, "pbFlag": false, "pbOverHistory": 0.4604, "peOverHistory": 0.1136, "date": "07-14"}, {"code": "CSI716567", "name": "MSCI\u4e2d\u56fd", "ttype": "1", "pe": 15.5539, "pb": 1.5713, "pePercentile": 0.883, "pbPercentile": 0.7325, "roe": 0.101, "yeild": 0.0243, "ts": 1783958400000, "evaType": "high", "evaTypeInt": 2, "bondYeild": 0.05, "beginAt": 1508688000000, "createdAt": 1784043123084, "updatedAt": 1784043123084, "pbFlag": false, "pbOverHistory": 0.2675, "peOverHistory": 0.117, "date": "07-14"}, {"code": "SPCQVCP", "name": "\u6807\u666e\u8d28\u91cf", "ttype": "2", "pe": 15.6419, "pb": 2.777, "pePercentile": 0.4024, "pbPercentile": 0.3848, "roe": 0.1775, "yeild": 0.0208, "ts": 1783958400000, "evaType": "high", "evaTypeInt": 2, "bondYeild": 0.05, "beginAt": 1459353600000, "createdAt": 1784025120305, "updatedAt": 1784025120305, "pbFlag": false, "pbOverHistory": 0.6152, "peOverHistory": 0.5976, "date": "07-14"}, {"code": "SH000903", "name": "\u4e2d\u8bc1100", "ttype": "1", "pe": 17.9714, "pb": 1.9331, "pePercentile": 0.9836, "pbPercentile": 0.9952, "roe": 0.1076, "yeild": 0.0257, "ts": 1783958400000, "evaType": "high", "evaTypeInt": 2, "bondYeild": 0.05, "beginAt": 1459353600000, "createdAt": 1784043121646, "updatedAt": 1784043121646, "pbFlag": false, "pbOverHistory": 0.0048, "peOverHistory": 0.0164, "date": "07-14"}, {"code": "GDAXI", "name": "\u5fb7\u56fdDAX", "ttype": "1", "pe": 18.009, "pb": 1.6996, "pePercentile": 0.5308, "pbPercentile": 0.5444, "roe": 0.0944, "yeild": 0.0011, "ts": 1783958400000, "evaType": "high", "evaTypeInt": 2, "bondYeild": 0.05, "beginAt": 1459267200000, "createdAt": 1784025124679, "updatedAt": 1784025124679, "pbFlag": false, "pbOverHistory": 0.4556, "peOverHistory": 0.4692, "date": "07-14"}, {"code": "SZ399324", "name": "\u6df1\u8bc1\u7ea2\u5229", "ttype": "2", "pe": 18.2435, "pb": 2.8307, "pePercentile": 0.8504, "pbPercentile": 0.9044, "roe": 0.1552, "yeild": 0.0357, "ts": 1783958400000, "evaType": "high", "evaTypeInt": 2, "bondYeild": 0.05, "beginAt": 1459353600000, "createdAt": 1784025122334, "updatedAt": 1784025122334, "pbFlag": false, "pbOverHistory": 0.0956, "peOverHistory": 0.1496, "date": "07-14"}, {"code": "SPHCMSHP", "name": "\u9999\u6e2f\u4e2d\u5c0f", "ttype": "1", "pe": 19.2896, "pb": 1.313, "pePercentile": 0.9478, "pbPercentile": 0.5206, "roe": 0.0681, "yeild": 0.0249, "ts": 1783958400000, "evaType": "high", "evaTypeInt": 2, "bondYeild": 0.05, "beginAt": 1467907200000, "createdAt": 1784079121345, "updatedAt": 1784079121345, "pbFlag": false, "pbOverHistory": 0.4794, "peOverHistory": 0.0522, "date": "07-14"}, {"code": "CSI931142", "name": "\u4e1c\u8bc1\u7ade\u4e89", "ttype": "2", "pe": 19.8619, "pb": 2.9981, "pePercentile": 0.9364, "pbPercentile": 0.8968, "roe": 0.1509, "yeild": 0.0229, "ts": 1783958400000, "evaType": "high", "evaTypeInt": 2, "bondYeild": 0.05, "beginAt": 1459353600000, "createdAt": 1784043122521, "updatedAt": 1784043122521, "pbFlag": false, "pbOverHistory": 0.1032, "peOverHistory": 0.0636, "date": "07-14"}, {"code": "SZ399998", "name": "\u4e2d\u8bc1\u7164\u70ad", "ttype": "3", "pe": 20.3915, "pb": 1.6559, "pePercentile": 0.868, "pbPercentile": 0.8708, "roe": 0.0812, "yeild": 0.0335, "ts": 1783958400000, "evaType": "high", "evaTypeInt": 2, "bondYeild": 0.05, "beginAt": 1456156800000, "createdAt": 1784025121420, "updatedAt": 1784025121420, "pbFlag": true, "pbOverHistory": 0.1292, "peOverHistory": 0.132, "date": "07-14"}, {"code": "CSI930782", "name": "500\u4f4e\u6ce2", "ttype": "2", "pe": 20.5125, "pb": 1.6719, "pePercentile": 0.5316, "pbPercentile": 0.708, "roe": 0.0815, "yeild": 0.0235, "ts": 1783958400000, "evaType": "high", "evaTypeInt": 2, "bondYeild": 0.05, "beginAt": 1459353600000, "createdAt": 1784025122409, "updatedAt": 1784025122409, "pbFlag": false, "pbOverHistory": 0.292, "peOverHistory": 0.4684, "date": "07-14"}, {"code": "SZ399317", "name": "\u56fd\u8bc1A\u6307", "ttype": "1", "pe": 22.1388, "pb": 1.8223, "pePercentile": 0.9524, "pbPercentile": 0.5844, "roe": 0.0823, "yeild": 0.0187, "ts": 1783958400000, "evaType": "high", "evaTypeInt": 2, "bondYeild": 0.05, "beginAt": 1459353600000, "createdAt": 1784043121845, "updatedAt": 1784043121845, "pbFlag": false, "pbOverHistory": 0.4156, "peOverHistory": 0.0476, "date": "07-14"}, {"code": "SZ399701", "name": "\u57fa\u672c\u976260", "ttype": "2", "pe": 22.2281, "pb": 2.0427, "pePercentile": 0.8076, "pbPercentile": 0.264, "roe": 0.0919, "yeild": 0.0279, "ts": 1783958400000, "evaType": "high", "evaTypeInt": 2, "bondYeild": 0.05, "beginAt": 1459353600000, "createdAt": 1784025122858, "updatedAt": 1784025122858, "pbFlag": false, "pbOverHistory": 0.736, "peOverHistory": 0.1924, "date": "07-14"}, {"code": "HKHSSCNE", "name": "\u65b0\u7ecf\u6d4e", "ttype": "2", "pe": 22.8864, "pb": 2.6876, "pePercentile": 0.3927, "pbPercentile": 0.3932, "roe": 0.1174, "yeild": 0.0098, "ts": 1783958400000, "evaType": "high", "evaTypeInt": 2, "bondYeild": 0.05, "beginAt": 1542729600000, "createdAt": 1784079121847, "updatedAt": 1784079121847, "pbFlag": false, "pbOverHistory": 0.6068, "peOverHistory": 0.6073, "date": "07-14"}, {"code": "HKHSTECH", "name": "\u6052\u751f\u79d1\u6280", "ttype": "3", "pe": 22.9627, "pb": 2.5712, "pePercentile": 0.3421, "pbPercentile": 0.3614, "roe": 0.112, "yeild": 0.0096, "ts": 1783958400000, "evaType": "high", "evaTypeInt": 2, "bondYeild": 0.05, "beginAt": 1595779200000, "createdAt": 1784043123453, "updatedAt": 1784043123453, "pbFlag": false, "pbOverHistory": 0.6386, "peOverHistory": 0.6579, "date": "07-14"}, {"code": "SZ399417", "name": "\u65b0\u80fd\u6e90\u8f66", "ttype": "3", "pe": 26.0254, "pb": 3.4625, "pePercentile": 0.376, "pbPercentile": 0.4876, "roe": 0.133, "yeild": 0.0142, "ts": 1783958400000, "evaType": "high", "evaTypeInt": 2, "bondYeild": 0.05, "beginAt": 1459353600000, "createdAt": 1784043122356, "updatedAt": 1784043122356, "pbFlag": true, "pbOverHistory": 0.5124, "peOverHistory": 0.624, "date": "07-14"}, {"code": "SZ399702", "name": "\u57fa\u672c\u9762120", "ttype": "2", "pe": 26.0961, "pb": 2.288, "pePercentile": 0.9696, "pbPercentile": 0.6548, "roe": 0.0877, "yeild": 0.0218, "ts": 1783958400000, "evaType": "high", "evaTypeInt": 2, "bondYeild": 0.05, "beginAt": 1459353600000, "createdAt": 1784025122932, "updatedAt": 1784025122932, "pbFlag": false, "pbOverHistory": 0.3452, "peOverHistory": 0.0304, "date": "07-14"}, {"code": "SP500", "name": "\u6807\u666e500", "ttype": "1", "pe": 28.3518, "pb": 5.7756, "pePercentile": 0.7996, "pbPercentile": 0.994, "roe": 0.2037, "yeild": 0.0102, "ts": 1783958400000, "evaType": "high", "evaTypeInt": 2, "bondYeild": 0.05, "beginAt": 1459353600000, "createdAt": 1784079120260, "updatedAt": 1784079120260, "pbFlag": false, "pbOverHistory": 0.006, "peOverHistory": 0.2004, "date": "07-14"}, {"code": "SZ399330", "name": "\u6df1\u8bc1100", "ttype": "1", "pe": 29.7667, "pb": 3.221, "pePercentile": 0.872, "pbPercentile": 0.7464, "roe": 0.1082, "yeild": 0.0171, "ts": 1783958400000, "evaType": "high", "evaTypeInt": 2, "bondYeild": 0.05, "beginAt": 1459353600000, "createdAt": 1784043120603, "updatedAt": 1784043120603, "pbFlag": false, "pbOverHistory": 0.2536, "peOverHistory": 0.128, "date": "07-14"}, {"code": "SH000827", "name": "\u4e2d\u8bc1\u73af\u4fdd", "ttype": "3", "pe": 31.9989, "pb": 2.5991, "pePercentile": 0.6644, "pbPercentile": 0.4144, "roe": 0.0812, "yeild": 0.0168, "ts": 1783958400000, "evaType": "high", "evaTypeInt": 2, "bondYeild": 0.05, "beginAt": 1459353600000, "createdAt": 1784025121182, "updatedAt": 1784025121182, "pbFlag": false, "pbOverHistory": 0.5856, "peOverHistory": 0.3356, "date": "07-14"}, {"code": "935600", "name": "MSCI\u5370\u5ea6", "ttype": "1", "pe": 35.4442, "pb": 4.7774, "pePercentile": 0.7792, "pbPercentile": 0.7792, "roe": 0.1348, "yeild": 0.0097, "ts": 1783958400000, "evaType": "high", "evaTypeInt": 2, "bondYeild": 0.05, "beginAt": 1481558400000, "createdAt": 1784025124592, "updatedAt": 1784025124592, "pbFlag": false, "pbOverHistory": 0.2208, "peOverHistory": 0.2208, "date": "07-14"}, {"code": "SZ399001", "name": "\u6df1\u8bc1\u6210\u6307", "ttype": "1", "pe": 35.5702, "pb": 3.0237, "pePercentile": 0.9812, "pbPercentile": 0.6692, "roe": 0.085, "yeild": 0.0141, "ts": 1783958400000, "evaType": "high", "evaTypeInt": 2, "bondYeild": 0.05, "beginAt": 1459353600000, "createdAt": 1784043122189, "updatedAt": 1784043122189, "pbFlag": false, "pbOverHistory": 0.3308, "peOverHistory": 0.0188, "date": "07-14"}, {"code": "NDX", "name": "\u7eb3\u6307100", "ttype": "1", "pe": 35.7277, "pb": 10.4867, "pePercentile": 0.8056, "pbPercentile": 0.9944, "roe": 0.2935, "yeild": 0.0043, "ts": 1783958400000, "evaType": "high", "evaTypeInt": 2, "bondYeild": 0.05, "beginAt": 1459267200000, "createdAt": 1784079120420, "updatedAt": 1784079120420, "pbFlag": false, "pbOverHistory": 0.0056, "peOverHistory": 0.1944, "date": "07-14"}, {"code": "SH000905", "name": "\u4e2d\u8bc1500", "ttype": "1", "pe": 38.8459, "pb": 2.6077, "pePercentile": 0.8888, "pbPercentile": 0.8332, "roe": 0.0671, "yeild": 0.0128, "ts": 1783958400000, "evaType": "high", "evaTypeInt": 2, "bondYeild": 0.05, "beginAt": 1459353600000, "createdAt": 1784043120433, "updatedAt": 1784043120433, "pbFlag": false, "pbOverHistory": 0.1668, "peOverHistory": 0.1112, "date": "07-14"}, {"code": "SH000852", "name": "\u4e2d\u8bc11000", "ttype": "1", "pe": 47.623, "pb": 2.5302, "pePercentile": 0.764, "pbPercentile": 0.5476, "roe": 0.0531, "yeild": 0.0103, "ts": 1783958400000, "evaType": "high", "evaTypeInt": 2, "bondYeild": 0.05, "beginAt": 1459353600000, "createdAt": 1784025120855, "updatedAt": 1784025120855, "pbFlag": false, "pbOverHistory": 0.4524, "peOverHistory": 0.236, "date": "07-14"}, {"code": "SZ399006", "name": "\u521b\u4e1a\u677f", "ttype": "1", "pe": 48.724, "pb": 6.4882, "pePercentile": 0.6168, "pbPercentile": 0.7944, "roe": 0.1332, "yeild": 0.0082, "ts": 1783958400000, "evaType": "high", "evaTypeInt": 2, "bondYeild": 0.05, "beginAt": 1459353600000, "createdAt": 1784043120693, "updatedAt": 1784043120693, "pbFlag": false, "pbOverHistory": 0.2056, "peOverHistory": 0.3832, "date": "07-14"}, {"code": "SZ399610", "name": "TMT50", "ttype": "3", "pe": 54.7331, "pb": 7.4311, "pePercentile": 0.9628, "pbPercentile": 0.9924, "roe": 0.1358, "yeild": 0.0062, "ts": 1783958400000, "evaType": "high", "evaTypeInt": 2, "bondYeild": 0.05, "beginAt": 1492790400000, "createdAt": 1784025123696, "updatedAt": 1784025123696, "pbFlag": false, "pbOverHistory": 0.0076, "peOverHistory": 0.0372, "date": "07-14"}, {"code": "CSI931079", "name": "5G\u901a\u8baf", "ttype": "3", "pe": 63.3156, "pb": 8.8155, "pePercentile": 0.988, "pbPercentile": 0.9857, "roe": 0.1392, "yeild": 0.0051, "ts": 1783958400000, "evaType": "high", "evaTypeInt": 2, "bondYeild": 0.05, "beginAt": 1556553600000, "createdAt": 1784025124319, "updatedAt": 1784025124319, "pbFlag": false, "pbOverHistory": 0.0143, "peOverHistory": 0.012, "date": "07-14"}, {"code": "SZ399967", "name": "\u4e2d\u8bc1\u519b\u5de5", "ttype": "3", "pe": 64.2868, "pb": 3.363, "pePercentile": 0.4712, "pbPercentile": 0.6016, "roe": 0.0523, "yeild": 0.0041, "ts": 1783958400000, "evaType": "high", "evaTypeInt": 2, "bondYeild": 0.05, "beginAt": 1459353600000, "createdAt": 1784025121491, "updatedAt": 1784025121491, "pbFlag": true, "pbOverHistory": 0.3984, "peOverHistory": 0.5288, "date": "07-14"}, {"code": "CSI931087", "name": "\u79d1\u6280\u9f99\u5934", "ttype": "3", "pe": 69.8672, "pb": 9.8351, "pePercentile": 0.991, "pbPercentile": 0.9899, "roe": 0.1408, "yeild": 0.0044, "ts": 1783958400000, "evaType": "high", "evaTypeInt": 2, "bondYeild": 0.05, "beginAt": 1553011200000, "createdAt": 1784043122658, "updatedAt": 1784043122658, "pbFlag": false, "pbOverHistory": 0.0101, "peOverHistory": 0.009, "date": "07-14"}, {"code": "CSI930652", "name": "\u4e2d\u8bc1\u7535\u5b50", "ttype": "3", "pe": 77.5769, "pb": 8.0937, "pePercentile": 0.9948, "pbPercentile": 0.9928, "roe": 0.1043, "yeild": 0.0049, "ts": 1783958400000, "evaType": "high", "evaTypeInt": 2, "bondYeild": 0.05, "beginAt": 1459267200000, "createdAt": 1784043123162, "updatedAt": 1784043123162, "pbFlag": false, "pbOverHistory": 0.0072, "peOverHistory": 0.0052, "date": "07-14"}, {"code": "SH000993", "name": "\u5168\u6307\u4fe1\u606f", "ttype": "3", "pe": 80.5028, "pb": 7.7919, "pePercentile": 0.9544, "pbPercentile": 0.9928, "roe": 0.0968, "yeild": 0.0049, "ts": 1783958400000, "evaType": "high", "evaTypeInt": 2, "bondYeild": 0.05, "beginAt": 1459353600000, "createdAt": 1784043121366, "updatedAt": 1784043121366, "pbFlag": false, "pbOverHistory": 0.0072, "peOverHistory": 0.0456, "date": "07-14"}, {"code": "SH000688", "name": "\u79d1\u521b50", "ttype": "1", "pe": 243.63, "pb": 9.5874, "pePercentile": 0.9956, "pbPercentile": 0.9937, "roe": 0.0394, "yeild": 0.0018, "ts": 1783958400000, "evaType": "high", "evaTypeInt": 2, "bondYeild": 0.05, "beginAt": 1577721600000, "createdAt": 1784043123268, "updatedAt": 1784043123268, "pbFlag": false, "pbOverHistory": 0.0063, "peOverHistory": 0.0044, "date": "07-14"}]