[{"title": "2026年第一季度广州房地产市场回顾", "org_name": "世邦魏理仕", "publish_date": "2026-04-16", "industry_name": "房地产开发", "pdf_url": "https://pdf.dfcfw.com/pdf/H3_AP202604151821247439_1.pdf?1776324175000.pdf"}, {"title": "汽车行业：中国汽车工业协会信息发布会", "org_name": "中国汽车工业协会", "publish_date": "2026-04-16", "industry_name": "汽车服务", "pdf_url": "https://pdf.dfcfw.com/pdf/H3_AP202604151821247440_1.pdf?1776325863000.pdf"}, {"title": "OpenClaw类智能体部署风险管理指南", "org_name": "中国人工智能产业发展联盟", "publish_date": "2026-04-16", "industry_name": "软件开发", "pdf_url": "https://pdf.dfcfw.com/pdf/H3_AP202604151821247438_1.pdf?1776325090000.pdf"}, {"title": "2026中国航空发动机MRO行业研究：需求上行、供给稀缺与国产替代驱动下的投资机会", "org_name": "上海久挚管理咨询", "publish_date": "2026-04-16", "industry_name": "航空装备Ⅱ", "pdf_url": "https://pdf.dfcfw.com/pdf/H3_AP202604151821247442_1.pdf?1776328520000.pdf"}, {"title": "寻找第二增长曲线：2026出海品牌平台迁移白皮书", "org_name": "尼尔森", "publish_date": "2026-04-16", "industry_name": "互联网电商", "pdf_url": "https://pdf.dfcfw.com/pdf/H3_AP202604151821247446_1.pdf?1776326645000.pdf"}, {"title": "金融网络安全运营数智化建设研究与实践", "org_name": "北京金融科技产业联盟", "publish_date": "2026-04-16", "industry_name": "多元金融", "pdf_url": "https://pdf.dfcfw.com/pdf/H3_AP202604151821247444_1.pdf?1776327340000.pdf"}, {"title": "海南旅游目的地型购物中心发展白皮书：展商旅融合，打造旅游目的地型购物中心", "org_name": "安永(中国)企业咨询", "publish_date": "2026-04-16", "industry_name": "旅游零售Ⅱ", "pdf_url": "https://pdf.dfcfw.com/pdf/H3_AP202604151821247445_1.pdf?1776327130000.pdf"}, {"title": "扩大健康领域的人工智能应用", "org_name": "经合组织", "publish_date": "2026-04-16", "industry_name": "IT服务Ⅱ", "pdf_url": "https://pdf.dfcfw.com/pdf/H3_AP202604151821247449_1.pdf?1776326460000.pdf"}, {"title": "女青年车市洞察报告（2026版）：女青年“掰弯”车企年轻化战略", "org_name": "腾易研究院", "publish_date": "2026-04-16", "industry_name": "汽车零部件", "pdf_url": "https://pdf.dfcfw.com/pdf/H3_AP202604151821247453_1.pdf?1776326388000.pdf"}, {"title": "医疗投资与成果：在中央和东欧", "org_name": "欧洲制药工业协会联合会", "publish_date": "2026-04-16", "industry_name": "医疗服务", "pdf_url": "https://pdf.dfcfw.com/pdf/H3_AP202604151821247436_1.pdf?1776325786000.pdf"}, {"title": "2026年中国公共服务平台运营行业市场研究报告", "org_name": "硕远咨询", "publish_date": "2026-04-16", "industry_name": "软件开发", "pdf_url": "https://pdf.dfcfw.com/pdf/H3_AP202604161821252004_1.pdf?1776328876000.pdf"}, {"title": "2026在家下厨烹饪消费电商数据报告-Nint任拓", "org_name": "泰安尚道网络科技", "publish_date": "2026-04-16", "industry_name": "食品加工", "pdf_url": "https://pdf.dfcfw.com/pdf/H3_AP202604151821247447_1.pdf?1776325973000.pdf"}, {"title": "2026年GEO行业专题研究报告：专注构建长效信任生态", "org_name": "艾瑞股份", "publish_date": "2026-04-16", "industry_name": "软件开发", "pdf_url": "https://pdf.dfcfw.com/pdf/H3_AP202604151821247895_1.pdf?1776324909000.pdf"}, {"title": "锂电3月洞察：聚焦能源自主主线，把握钠电储能机遇", "org_name": "国金证券", "publish_date": "2026-04-16", "industry_name": "电池", "pdf_url": "https://pdf.dfcfw.com/pdf/H3_AP202604161821252138_1.pdf?1776329142000.pdf"}, {"title": "人形机器人周报：强脑灵巧手亮相，千寻智能再融10亿", "org_name": "国元证券", "publish_date": "2026-04-16", "industry_name": "自动化设备", "pdf_url": "https://pdf.dfcfw.com/pdf/H3_AP202604161821251336_1.pdf?1776325786000.pdf"}, {"title": "2026年中国影视行业网络保护研究报告", "org_name": "艾瑞股份", "publish_date": "2026-04-16", "industry_name": "数字媒体", "pdf_url": "https://pdf.dfcfw.com/pdf/H3_AP202604161821253378_1.pdf?1776332755000.pdf"}, {"title": "2026年中国社区养老服务行业市场研究报告", "org_name": "硕远咨询", "publish_date": "2026-04-16", "industry_name": "专业服务", "pdf_url": "https://pdf.dfcfw.com/pdf/H3_AP202604161821252007_1.pdf?1776329028000.pdf"}, {"title": "有色金属USGS 2025年数据洞察：关注战略矿产，掌握资源主导权", "org_name": "五矿证券", "publish_date": "2026-04-16", "industry_name": "工业金属", "pdf_url": "https://pdf.dfcfw.com/pdf/H3_AP202604161821255834_1.pdf?1776342119000.pdf"}, {"title": "非银金融：深化创业板改革，做好“科技金融”大文章", "org_name": "五矿证券", "publish_date": "2026-04-16", "industry_name": "证券Ⅱ", "pdf_url": "https://pdf.dfcfw.com/pdf/H3_AP202604161821255817_1.pdf?1776342038000.pdf"}, {"title": "农林牧渔行业：南非一型口蹄疫传入，关注畜牧业供给收缩和疫苗进展", "org_name": "东兴证券", "publish_date": "2026-04-16", "industry_name": "养殖业", "pdf_url": "https://pdf.dfcfw.com/pdf/H3_AP202604161821255837_1.pdf?1776341676000.pdf"}, {"title": "银行行业3月社融金融数据点评：信贷需求待修复，居民存款搬家显现趋势", "org_name": "东兴证券", "publish_date": "2026-04-16", "industry_name": "银行Ⅱ", "pdf_url": "https://pdf.dfcfw.com/pdf/H3_AP202604161821254365_1.pdf?1776335595000.pdf"}, {"title": "AI应用追寻系列报告（四）：AI电商，海外巨头是如何实践的？", "org_name": "华源证券", "publish_date": "2026-04-16", "industry_name": "互联网电商", "pdf_url": "https://pdf.dfcfw.com/pdf/H3_AP202604161821256733_1.pdf?1776345434000.pdf"}, {"title": "医药生物行业周报：分级诊疗体系迎重要部署，关注基层医疗资源配置优化、服务能力提升", "org_name": "上海证券", "publish_date": "2026-04-16", "industry_name": "生物制品", "pdf_url": "https://pdf.dfcfw.com/pdf/H3_AP202604161821253937_1.pdf?1776334661000.pdf"}]