[{"title": "非银行业点评：阶段性高赔付持续，新政后高质量发展可期", "org_name": "民生证券", "publish_date": "2025-01-27", "industry_name": "保险", "pdf_url": "https://pdf.dfcfw.com/pdf/H3_AP202501261642575556_1.pdf?1737962333000.pdf"}, {"title": "机械设备行业周报：人形机器人走向2025：巨头云集的主赛道，把握核心主线和节奏", "org_name": "开源证券", "publish_date": "2025-01-27", "industry_name": "通用设备", "pdf_url": "https://pdf.dfcfw.com/pdf/H3_AP202501271642577174_1.pdf?1737968028000.pdf"}, {"title": "非银金融：中长期资金系列研究（一）-落实长周期考核，助力培育耐心资本", "org_name": "东海证券", "publish_date": "2025-01-27", "industry_name": "保险", "pdf_url": "https://pdf.dfcfw.com/pdf/H3_AP202501271642577208_1.pdf?1737962975000.pdf"}, {"title": "非银金融行业跟踪周报：中长期资金入市可期；新能源车险指导意见出台", "org_name": "东吴证券", "publish_date": "2025-01-27", "industry_name": "证券", "pdf_url": "https://pdf.dfcfw.com/pdf/H3_AP202501271642577206_1.pdf?1737939159000.pdf"}, {"title": "环保行业跟踪周报：加快制造业低碳转型，聚焦绿色技术装备&循环利用，持续推荐水务固废现金流资产", "org_name": "东吴证券", "publish_date": "2025-01-27", "industry_name": "环保行业", "pdf_url": "https://pdf.dfcfw.com/pdf/H3_AP202501271642577210_1.pdf?1737970488000.pdf"}, {"title": "煤炭行业周报：煤炭市场平稳运行，继续关注红利投资机会", "org_name": "大同证券", "publish_date": "2025-01-27", "industry_name": "煤炭行业", "pdf_url": "https://pdf.dfcfw.com/pdf/H3_AP202501271642583829_1.pdf?1737965064000.pdf"}, {"title": "电力设备行业跟踪周报：人形机器人量产落地超预期、锂电龙头盈利修复可期", "org_name": "东吴证券", "publish_date": "2025-01-27", "industry_name": "电池", "pdf_url": "https://pdf.dfcfw.com/pdf/H3_AP202501271642577204_1.pdf?1737970087000.pdf"}, {"title": "电力设备及新能源行业周报：产业周跟踪，分布式光伏新政促进量质齐升，欧盟拟出台电车补贴计划", "org_name": "华福证券", "publish_date": "2025-01-27", "industry_name": "电池", "pdf_url": "https://pdf.dfcfw.com/pdf/H3_AP202501271642584007_1.pdf?1737965520000.pdf"}, {"title": "医药行业周报：艾司氯胺酮单药疗法获批，难治性抑郁症快速改善", "org_name": "太平洋", "publish_date": "2025-01-27", "industry_name": "化学制药", "pdf_url": "https://pdf.dfcfw.com/pdf/H3_AP202501271642583987_1.pdf?1737965334000.pdf"}, {"title": "农林牧渔行业定期报告：节前猪价震荡上行，仔猪价格继续走强", "org_name": "华福证券", "publish_date": "2025-01-27", "industry_name": "农牧饲渔", "pdf_url": "https://pdf.dfcfw.com/pdf/H3_AP202501271642584012_1.pdf?1737965520000.pdf"}, {"title": "电力设备及新能源行业周报：陕西光伏领跑计划有利于BC电池，大储迈向“双6”时代", "org_name": "平安证券", "publish_date": "2025-01-27", "industry_name": "电池", "pdf_url": "https://pdf.dfcfw.com/pdf/H3_AP202501271642584033_1.pdf?1737965805000.pdf"}, {"title": "计算机行业：国产大模型持续迭代升级，应用落地步伐有望加速", "org_name": "平安证券", "publish_date": "2025-01-27", "industry_name": "软件开发", "pdf_url": "https://pdf.dfcfw.com/pdf/H3_AP202501271642584034_1.pdf?1737967685000.pdf"}, {"title": "交通运输产业行业研究：2024Q4交运持仓环比调整 12月快递业务量增长22.3%", "org_name": "国金证券", "publish_date": "2025-01-27", "industry_name": "物流行业", "pdf_url": "https://pdf.dfcfw.com/pdf/H3_AP202501271642584166_1.pdf?1737977429000.pdf"}, {"title": "汽车及汽车零部件行业周报：激光雷达龙头跑马圈地，人行机器人商业化突破在即", "org_name": "国金证券", "publish_date": "2025-01-27", "industry_name": "汽车零部件", "pdf_url": "https://pdf.dfcfw.com/pdf/H3_AP202501271642584168_1.pdf?1737966159000.pdf"}, {"title": "生物医药行业：多家药企披露2024年业绩预告，部分创新药企表现亮眼", "org_name": "平安证券", "publish_date": "2025-01-27", "industry_name": "化学制药", "pdf_url": "https://pdf.dfcfw.com/pdf/H3_AP202501271642584035_1.pdf?1737976980000.pdf"}, {"title": "机器人行业周报（0120-0126）：云深处发布机器狗山猫视频，看好四足机器狗商业化进程", "org_name": "西南证券", "publish_date": "2025-01-27", "industry_name": "通用设备", "pdf_url": "https://pdf.dfcfw.com/pdf/H3_AP202501271642585004_1.pdf?1737968430000.pdf"}, {"title": "计算机行业周报：Open AI发布AI Agent Operator，AI应用落地加速", "org_name": "国金证券", "publish_date": "2025-01-27", "industry_name": "互联网服务", "pdf_url": "https://pdf.dfcfw.com/pdf/H3_AP202501271642584169_1.pdf?1737966159000.pdf"}, {"title": "医药行业周报：药品反垄断法出台，业绩预报持续落地", "org_name": "西南证券", "publish_date": "2025-01-27", "industry_name": "中药", "pdf_url": "https://pdf.dfcfw.com/pdf/H3_AP202501271642585005_1.pdf?1737968430000.pdf"}, {"title": "国防军工行业报告：66家军工行业上市公司披露业绩预告，14家2024年业绩正增长", "org_name": "中邮证券", "publish_date": "2025-01-27", "industry_name": "航天航空", "pdf_url": "https://pdf.dfcfw.com/pdf/H3_AP202501271642586071_1.pdf?1737970087000.pdf"}, {"title": "轻工纺服行业周报：轻工出口龙头业绩亮眼，看好25年海外订单持续", "org_name": "上海证券", "publish_date": "2025-01-27", "industry_name": "纺织服装", "pdf_url": "https://pdf.dfcfw.com/pdf/H3_AP202501271642586074_1.pdf?1737970087000.pdf"}, {"title": "美容护理行业周报：24年业绩预告陆续披露，关注业绩兑现能力", "org_name": "上海证券", "publish_date": "2025-01-27", "industry_name": "美容护理", "pdf_url": "https://pdf.dfcfw.com/pdf/H3_AP202501271642586073_1.pdf?1737970087000.pdf"}, {"title": "社会服务行业周报：推动中长期资金入市，国货美业稳健发展", "org_name": "平安证券", "publish_date": "2025-01-27", "industry_name": "旅游酒店", "pdf_url": "https://pdf.dfcfw.com/pdf/H3_AP202501271642588012_1.pdf?1737974175000.pdf"}, {"title": "食品饮料行业周报：龙头公司业绩优异，关注春节表现", "org_name": "上海证券", "publish_date": "2025-01-27", "industry_name": "酿酒行业", "pdf_url": "https://pdf.dfcfw.com/pdf/H3_AP202501271642586075_1.pdf?1737970087000.pdf"}, {"title": "通信行业周报：5000亿美元“星际之门”启动，兼顾硬件及端侧", "org_name": "国元证券", "publish_date": "2025-01-27", "industry_name": "通信设备", "pdf_url": "https://pdf.dfcfw.com/pdf/H3_AP202501271642588456_1.pdf?1737976289000.pdf"}, {"title": "AI周观察：AI领域投资计划引发关注，HBM景气度高", "org_name": "国金证券", "publish_date": "2025-01-27", "industry_name": "计算机设备", "pdf_url": "https://pdf.dfcfw.com/pdf/H3_AP202501271642586523_1.pdf?1737972344000.pdf"}]